autopost/__init__.py
autopost/_cli.py
autopost/_config.py
autopost/_backend/__init__.py
autopost/_backend/bluesky.py
autopost/_backend/dummy.py
autopost/_backend/interface.py
autopost/_backend/mastodon.py
autopost/_backend/reddit.py
autopost/_backend/twitter.py
autopost-0.0.10.dist-info/LICENSE
autopost-0.0.10.dist-info/METADATA
autopost-0.0.10.dist-info/WHEEL
autopost-0.0.10.dist-info/entry_points.txt
autopost-0.0.10.dist-info/top_level.txt
autopost-0.0.10.dist-info/RECORD
