Metadata-Version: 2.2
Name: autopost
Version: 0.0.10
Summary: Auto-posts social media updates
Author-email: William Woodruff <william@yossarian.net>
License: The MIT License (MIT)
Project-URL: Homepage, https://pypi.org/project/autopost/
Project-URL: Issues, https://github.com/woodruffw/autopost/issues
Project-URL: Source, https://github.com/woodruffw/autopost
Classifier: License :: OSI Approved :: MIT License
Classifier: Programming Language :: Python :: 3 :: Only
Classifier: Programming Language :: Python :: 3
Classifier: Development Status :: 4 - Beta
Classifier: Intended Audience :: Developers
Classifier: Topic :: Security
Requires-Python: >=3.11
License-File: LICENSE
Requires-Dist: atproto~=0.0.30
Requires-Dist: feedparser~=6.0
Requires-Dist: praw<7.9.0,>=7.6.1
Requires-Dist: Mastodon.py<1.9,>=1.7
Requires-Dist: pydantic<3.0,>=1.10
Requires-Dist: python-frontmatter~=1.0
Requires-Dist: result~=0.8
Requires-Dist: rich<13.10.0,>=12.5.1
Requires-Dist: python-twitter~=3.5
Provides-Extra: test
Requires-Dist: pytest; extra == "test"
Requires-Dist: pytest-cov; extra == "test"
Requires-Dist: pretend; extra == "test"
Provides-Extra: lint
Requires-Dist: bandit; extra == "lint"
Requires-Dist: interrogate; extra == "lint"
Requires-Dist: mypy; extra == "lint"
Requires-Dist: ruff; extra == "lint"
Provides-Extra: dev
Requires-Dist: build; extra == "dev"
Requires-Dist: autopost[lint,test]; extra == "dev"
